CHANGELOG.md
MANIFEST.in
README.md
setup.py
cli/__init__.py
cli/odoopbx_cli.py
cli/version.py
odoopbx.egg-info/PKG-INFO
odoopbx.egg-info/SOURCES.txt
odoopbx.egg-info/dependency_links.txt
odoopbx.egg-info/entry_points.txt
odoopbx.egg-info/not-zip-safe
odoopbx.egg-info/requires.txt
odoopbx.egg-info/top_level.txt
pillar/odoopbx.sls
pillar/systemd.sls
pillar/top.sls
pillar/virtual-container.sls
salt/odoopbx.sls
salt/test.sls
salt/top.sls
salt/uninstall.sls
salt/agent/config.sls
salt/agent/defaults.yaml
salt/agent/init.sls
salt/agent/install.sls
salt/agent/map.jinja
salt/agent/osfamilymap.yaml
salt/agent/osfingermap.yaml
salt/agent/service.sls
salt/agent/x509.sls
salt/agent/files/etc/master
salt/agent/files/etc/minion
salt/agent/files/etc/extensions/engines/asterisk_ami.py
salt/agent/files/etc/extensions/engines/asterisk_cli.py
salt/agent/files/etc/extensions/engines/asterisk_fastagi.py
salt/agent/files/etc/extensions/engines/odoo_executor.py
salt/agent/files/etc/extensions/modules/asteriskmod.py
salt/agent/files/etc/extensions/modules/ipset.py
salt/agent/files/etc/extensions/modules/odoomod.py
salt/agent/files/etc/extensions/returners/odoo_returner.py
salt/agent/files/etc/minion.d/odoopbx.conf
salt/agent/files/etc/odoopbx/.placeholder
salt/agent/files/etc/roots/firewall.sh
salt/agent/files/etc/roots/security.sls
salt/agent/files/systemd/salt-api.service
salt/agent/files/systemd/salt-master.service
salt/agent/files/systemd/salt-minion.service
salt/asterisk/compile.sls
salt/asterisk/configs.sls
salt/asterisk/defaults.yaml
salt/asterisk/init.sls
salt/asterisk/install.sls
salt/asterisk/libsaltcli.jinja
salt/asterisk/libtofs.jinja
salt/asterisk/map.jinja
salt/asterisk/osarchmap.yaml
salt/asterisk/osfamilymap.yaml
salt/asterisk/osfingermap.yaml
salt/asterisk/osmap.yaml
salt/asterisk/prereq.sls
salt/asterisk/service.sls
salt/asterisk/sounds.sls
salt/asterisk/sources.sls
salt/asterisk/uninstall.sls
salt/asterisk/files/asterisk.logrotate
salt/asterisk/files/asterisk.service
salt/asterisk/files/configs/acl.conf
salt/asterisk/files/configs/agents.conf
salt/asterisk/files/configs/ari.conf
salt/asterisk/files/configs/asterisk.conf
salt/asterisk/files/configs/ccss.conf
