Metadata-Version: 2.1
Name: odoopbx
Version: 1.13
Summary: Odoo PBX management application.
Home-page: https://gitlab.com/odoopbx
Author: Odooist
Author-email: odooist@gmail.com
License: Odoo Enterprise Edition License v1.0
Platform: UNKNOWN
Classifier: Development Status :: 5 - Production/Stable
Classifier: Intended Audience :: Developers
Classifier: Topic :: Software Development :: Build Tools
Classifier: License :: OSI Approved :: MIT License
Classifier: Programming Language :: Python :: 3
Classifier: Programming Language :: Python :: 3.6
Classifier: Programming Language :: Python :: 3.7
Classifier: Programming Language :: Python :: 3.8
